benchmarks/__init__.py
benchmarks/test_slovar_benchmark.py
slovar/__init__.py
slovar/convert.py
slovar/dictionaries.py
slovar/exceptions.py
slovar/json.py
slovar/lists.py
slovar/strings.py
slovar/utils.py
tests/__init__.py
tests/test_slovar.py
tests/test_slovar_complex.py
tests/test_utils.py
slovar-1.0.2.dist-info/LICENSE
slovar-1.0.2.dist-info/METADATA
slovar-1.0.2.dist-info/WHEEL
slovar-1.0.2.dist-info/top_level.txt
slovar-1.0.2.dist-info/RECORD
