Metadata-Version: 2.1
Name: slovar
Version: 1.0.2
Summary: slovar - dict on steroids
Home-page: UNKNOWN
Author: vahan
Author-email: aivosha@gmail.com
License: UNKNOWN
Keywords: dict slovar
Platform: UNKNOWN
Classifier: Programming Language :: Python
Requires-Dist: python-dateutil
Requires-Dist: bson
